api_inference_community/hub.py
api_inference_community/normalizers.py
api_inference_community/routes.py
api_inference_community/validation.py
api_inference_community-0.0.36.dist-info/LICENSE
api_inference_community-0.0.36.dist-info/METADATA
api_inference_community-0.0.36.dist-info/WHEEL
api_inference_community-0.0.36.dist-info/top_level.txt
api_inference_community-0.0.36.dist-info/RECORD
