Metadata-Version: 2.1
Name: api_inference_community
Version: 0.0.36
Summary: A package with helper tools to build an API Inference docker app for Hugging Face API inference using huggingface_hub
Home-page: http://github.com/huggingface/api-inference-community
Author: Nicolas Patry
Author-email: nicolas@huggingface.co
License: MIT
Requires-Python: >=3.6.0
License-File: LICENSE
Requires-Dist: starlette >=0.14.2
Requires-Dist: numpy >=1.18.0
Requires-Dist: pydantic >=2
Requires-Dist: parameterized >=0.8.1
Requires-Dist: pillow >=8.2.0
Requires-Dist: huggingface-hub >=0.20.2
Requires-Dist: datasets >=2.2
Requires-Dist: psutil >=6.0.0
Requires-Dist: pytest
Requires-Dist: httpx
Requires-Dist: uvicorn
Requires-Dist: black
Requires-Dist: isort
Requires-Dist: flake8
Provides-Extra: quality
Requires-Dist: black ==22.3.0 ; extra == 'quality'
Requires-Dist: isort ; extra == 'quality'
Requires-Dist: flake8 ; extra == 'quality'
Requires-Dist: mypy ; extra == 'quality'
Provides-Extra: test
Requires-Dist: httpx >=0.18 ; extra == 'test'
Requires-Dist: Pillow >=8.2 ; extra == 'test'
Requires-Dist: torch >=1.9.0 ; extra == 'test'
Requires-Dist: pytest >=6.2 ; extra == 'test'
